InstructionFetch/pcReg/pcReg.v
module PcReg(pcOut, pc, clk, rstn);
   input [31:0] pc;
   input	clk, rstn;
   output reg [31:0] pcOut;

   always@(posedge clk)
     begin
	pcOut = pc;
     end

   always@(negedge rstn)
     begin
	pcOut = 0;
     end

endmodule // main

InstructionFetch/pcReg/pcReg_test.v
`timescale 1ns / 1ps

module main_test;

   // Inputs
   reg [31:0] pc;
   reg	      clk, rstn;
   
   // Outputs
   wire [31:0] pcOut;

   integer i;
   // parameter size = 16;

   // Instantiate the Unit Under Test (UUT)
   PcReg uut(pcOut,
	     pc,
	     clk,
	     rstn
	      );

   initial begin
      /// Initialize Inputs
      #10 rstn = 1;
      rstn = 0;
      pc = 0;

      #100;
      pc = 4;

      // $readmemb("pth", 2d_reg, start_addr, end_addr);
   end

   initial begin
      clk = 0;
      for (i = 0; i < 2000; i = i + 1)
	#25 clk = ~clk;
   end


   initial begin
      $dumpfile("./pcReg_test.vcd");
      $dumpvars;
   end

endmodule

InstructionFetch/pcReg/pcReg_test.vcd
$date
	Tue Oct 23 20:27:56 2018
$end
$version
	Icarus Verilog
$end
$timescale
	1ps
$end
$scope module main_test $end
$var wire 32 ! pcOut [31:0] $end
$var reg 1 " clk $end
$var reg 32 # pc [31:0] $end
$var reg 1 $ rstn $end
$var integer 32 % i [31:0] $end
$scope module uut $end
$var wire 1 " clk $end
$var wire 32 & pc [31:0] $end
$var wire 1 $ rstn $end
$var reg 32 ' pcOut [31:0] $end
$upscope $end
$upscope $end
$enddefinitions $end
#0
$dumpvars
bx '
bx &
b0 %
x$
bx #
0"
bx !
$end
#10000
b0 !
b0 '
b0 #
b0 &
0$
#25000
b1 %
1"
#50000
b10 %
0"
#75000
b11 %
1"
#100000
b100 %
0"
#110000
b100 #
b100 &
#125000
b100 !
b100 '
b101 %
1"
#150000
b110 %
0"
#175000
b111 %
1"
#200000
b1000 %
0"
#225000
b1001 %
1"
#250000
b1010 %
0"
#275000
b1011 %
1"
#300000
b1100 %
0"
#325000
b1101 %
1"
#350000
b1110 %
0"
#375000
b1111 %
1"
#400000
b10000 %
0"
#425000
b10001 %
1"
#450000
b10010 %
0"
#475000
b10011 %
1"
#500000
b10100 %
0"
#525000
b10101 %
1"
#550000
b10110 %
0"
#575000
b10111 %
1"
#600000
b11000 %
0"
#625000
b11001 %
1"
#650000
b11010 %
0"
#675000
b11011 %
1"
#700000
b11100 %
0"
#725000
b11101 %
1"
#750000
b11110 %
0"
#775000
b11111 %
1"
#800000
b100000 %
0"
#825000
b100001 %
1"
#850000
b100010 %
0"
#875000
b100011 %
1"
#900000
b100100 %
0"
#925000
b100101 %
1"
#950000
b100110 %
0"
#975000
b100111 %
1"
#1000000
b101000 %
0"
#1025000
b101001 %
1"
#1050000
b101010 %
0"
#1075000
b101011 %
1"
#1100000
b101100 %
0"
#1125000
b101101 %
1"
#1150000
b101110 %
0"
#1175000
b101111 %
1"
#1200000
b110000 %
0"
#1225000
b110001 %
1"
#1250000
b110010 %
0"
#1275000
b110011 %
1"
#1300000
b110100 %
0"
#1325000
b110101 %
1"
#1350000
b110110 %
0"
#1375000
b110111 %
1"
#1400000
b111000 %
0"
#1425000
b111001 %
1"
#1450000
b111010 %
0"
#1475000
b111011 %
1"
#1500000
b111100 %
0"
#1525000
b111101 %
1"
#1550000
b111110 %
0"
#1575000
b111111 %
1"
#1600000
b1000000 %
0"
#1625000
b1000001 %
1"
#1650000
b1000010 %
0"
#1675000
b1000011 %
1"
#1700000
b1000100 %
0"
#1725000
b1000101 %
1"
#1750000
b1000110 %
0"
#1775000
b1000111 %
1"
#1800000
b1001000 %
0"
#1825000
b1001001 %
1"
#1850000
b1001010 %
0"
#1875000
b1001011 %
1"
#1900000
b1001100 %
0"
#1925000
b1001101 %
1"
#1950000
b1001110 %
0"
#1975000
b1001111 %
1"
#2000000
b1010000 %
0"
#2025000
b1010001 %
1"
#2050000
b1010010 %
0"
#2075000
b1010011 %
1"
#2100000
b1010100 %
0"
#2125000
b1010101 %
1"
#2150000
b1010110 %
0"
#2175000
b1010111 %
1"
#2200000
b1011000 %
0"
#2225000
b1011001 %
1"
#2250000
b1011010 %
0"
#2275000
b1011011 %
1"
#2300000
b1011100 %
0"
#2325000
b1011101 %
1"
#2350000
b1011110 %
0"
#2375000
b1011111 %
1"
#2400000
b1100000 %
0"
#2425000
b1100001 %
1"
#2450000
b1100010 %
0"
#2475000
b1100011 %
1"
#2500000
b1100100 %
0"
#2525000
b1100101 %
1"
#2550000
b1100110 %
0"
#2575000
b1100111 %
1"
#2600000
b1101000 %
0"
#2625000
b1101001 %
1"
#2650000
b1101010 %
0"
#2675000
b1101011 %
1"
#2700000
b1101100 %
0"
#2725000
b1101101 %
1"
#2750000
b1101110 %
0"
#2775000
b1101111 %
1"
#2800000
b1110000 %
0"
#2825000
b1110001 %
1"
#2850000
b1110010 %
0"
#2875000
b1110011 %
1"
#2900000
b1110100 %
0"
#2925000
b1110101 %
1"
#2950000
b1110110 %
0"
#2975000
b1110111 %
1"
#3000000
b1111000 %
0"
#3025000
b1111001 %
1"
#3050000
b1111010 %
0"
#3075000
b1111011 %
1"
#3100000
b1111100 %
0"
#3125000
b1111101 %
1"
#3150000
b1111110 %
0"
#3175000
b1111111 %
1"
#3200000
b10000000 %
0"
#3225000
b10000001 %
1"
#3250000
b10000010 %
0"
#3275000
b10000011 %
1"
#3300000
b10000100 %
0"
#3325000
b10000101 %
1"
#3350000
b10000110 %
0"
#3375000
b10000111 %
1"
#3400000
b10001000 %
0"
#3425000
b10001001 %
1"
#3450000
b10001010 %
0"
#3475000
b10001011 %
1"
#3500000
b10001100 %
0"
#3525000
b10001101 %
1"
#3550000
b10001110 %
0"
#3575000
b10001111 %
1"
#3600000
b10010000 %
0"
#3625000
b10010001 %
1"
#3650000
b10010010 %
0"
#3675000
b10010011 %
1"
#3700000
b10010100 %
0"
#3725000
b10010101 %
1"
#3750000
b10010110 %
0"
#3775000
b10010111 %
1"
#3800000
b10011000 %
0"
#3825000
b10011001 %
1"
#3850000
b10011010 %
0"
#3875000
b10011011 %
1"
#3900000
b10011100 %
0"
#3925000
b10011101 %
1"
#3950000
b10011110 %
0"
#3975000
b10011111 %
1"
#4000000
b10100000 %
0"
#4025000
b10100001 %
1"
#4050000
b10100010 %
0"
#4075000
b10100011 %
1"
#4100000
b10100100 %
0"
#4125000
b10100101 %
1"
#4150000
b10100110 %
0"
#4175000
b10100111 %
1"
#4200000
b10101000 %
0"
#4225000
b10101001 %
1"
#4250000
b10101010 %
0"
#4275000
b10101011 %
1"
#4300000
b10101100 %
0"
#4325000
b10101101 %
1"
#4350000
b10101110 %
0"
#4375000
b10101111 %
1"
#4400000
b10110000 %
0"
#4425000
b10110001 %
1"
#4450000
b10110010 %
0"
#4475000
b10110011 %
1"
#4500000
b10110100 %
0"
#4525000
b10110101 %
1"
#4550000
b10110110 %
0"
#4575000
b10110111 %
1"
#4600000
b10111000 %
0"
#4625000
b10111001 %
1"
#4650000
b10111010 %
0"
#4675000
b10111011 %
1"
#4700000
b10111100 %
0"
#4725000
b10111101 %
1"
#4750000
b10111110 %
0"
#4775000
b10111111 %
1"
#4800000
b11000000 %
0"
#4825000
b11000001 %
1"
#4850000
b11000010 %
0"
#4875000
b11000011 %
1"
#4900000
b11000100 %
0"
#4925000
b11000101 %
1"
#4950000
b11000110 %
0"
#4975000
b11000111 %
1"
#5000000
b11001000 %
0"
#5025000
b11001001 %
1"
#5050000
b11001010 %
0"
#5075000
b11001011 %
1"
#5100000
b11001100 %
0"
#5125000
b11001101 %
1"
#5150000
b11001110 %
0"
#5175000
b11001111 %
1"
#5200000
b11010000 %
0"
#5225000
b11010001 %
1"
#5250000
b11010010 %
0"
#5275000
b11010011 %
1"
#5300000
b11010100 %
0"
#5325000
b11010101 %
1"
#5350000
b11010110 %
0"
#5375000
b11010111 %
1"
#5400000
b11011000 %
0"
#5425000
b11011001 %
1"
#5450000
b11011010 %
0"
#5475000
b11011011 %
1"
#5500000
b11011100 %
0"
#5525000
b11011101 %
1"
#5550000
b11011110 %
0"
#5575000
b11011111 %
1"
#5600000
b11100000 %
0"
#5625000
b11100001 %
1"
#5650000
b11100010 %
0"
#5675000
b11100011 %
1"
#5700000
b11100100 %
0"
#5725000
b11100101 %
1"
#5750000
b11100110 %
0"
#5775000
b11100111 %
1"
#5800000
b11101000 %
0"
#5825000
b11101001 %
1"
#5850000
b11101010 %
0"
#5875000
b11101011 %
1"
#5900000
b11101100 %
0"
#5925000
b11101101 %
1"
#5950000
b11101110 %
0"
#5975000
b11101111 %
1"
#6000000
b11110000 %
0"
#6025000
b11110001 %
1"
#6050000
b11110010 %
0"
#6075000
b11110011 %
1"
#6100000
b11110100 %
0"
#6125000
b11110101 %
1"
#6150000
b11110110 %
0"
#6175000
b11110111 %
1"
#6200000
b11111000 %
0"
#6225000
b11111001 %
1"
#6250000
b11111010 %
0"
#6275000
b11111011 %
1"
#6300000
b11111100 %
0"
#6325000
b11111101 %
1"
#6350000
b11111110 %
0"
#6375000
b11111111 %
1"
#6400000
b100000000 %
0"
#6425000
b100000001 %
1"
#6450000
b100000010 %
0"
#6475000
b100000011 %
1"
#6500000
b100000100 %
0"
#6525000
b100000101 %
1"
#6550000
b100000110 %
0"
#6575000
b100000111 %
1"
#6600000
b100001000 %
0"
#6625000
b100001001 %
1"
#6650000
b100001010 %
0"
#6675000
b100001011 %
1"
#6700000
b100001100 %
0"
#6725000
b100001101 %
1"
#6750000
b100001110 %
0"
#6775000
b100001111 %
1"
#6800000
b100010000 %
0"
#6825000
b100010001 %
1"
#6850000
b100010010 %
0"
#6875000
b100010011 %
1"
#6900000
b100010100 %
0"
#6925000
b100010101 %
1"
#6950000
b100010110 %
0"
#6975000
b100010111 %
1"
#7000000
b100011000 %
0"
#7025000
b100011001 %
1"
#7050000
b100011010 %
0"
#7075000
b100011011 %
1"
#7100000
b100011100 %
0"
#7125000
b100011101 %
1"
#7150000
b100011110 %
0"
#7175000
b100011111 %
1"
#7200000
b100100000 %
0"
#7225000
b100100001 %
1"
#7250000
b100100010 %
0"
#7275000
b100100011 %
1"
#7300000
b100100100 %
0"
#7325000
b100100101 %
1"
#7350000
b100100110 %
0"
#7375000
b100100111 %
1"
#7400000
b100101000 %
0"
#7425000
b100101001 %
1"
#7450000
b100101010 %
0"
#7475000
b100101011 %
1"
#7500000
b100101100 %
0"
#7525000
b100101101 %
1"
#7550000
b100101110 %
0"
#7575000
b100101111 %
1"
#7600000
b100110000 %
0"
#7625000
b100110001 %
1"
#7650000
b100110010 %
0"
#7675000
b100110011 %
1"
#7700000
b100110100 %
0"
#7725000
b100110101 %
1"
#7750000
b100110110 %
0"
#7775000
b100110111 %
1"
#7800000
b100111000 %
0"
#7825000
b100111001 %
1"
#7850000
b100111010 %
0"
#7875000
b100111011 %
1"
#7900000
b100111100 %
0"
#7925000
b100111101 %
1"
#7950000
b100111110 %
0"
#7975000
b100111111 %
1"
#8000000
b101000000 %
0"
#8025000
b101000001 %
1"
#8050000
b101000010 %
0"
#8075000
b101000011 %
1"
#8100000
b101000100 %
0"
#8125000
b101000101 %
1"
#8150000
b101000110 %
0"
#8175000
b101000111 %
1"
#8200000
b101001000 %
0"
#8225000
b101001001 %
1"
#8250000
b101001010 %
0"
#8275000
b101001011 %
1"
#8300000
b101001100 %
0"
#8325000
b101001101 %
1"
#8350000
b101001110 %
0"
#8375000
b101001111 %
1"
#8400000
b101010000 %
0"
#8425000
b101010001 %
1"
#8450000
b101010010 %
0"
#8475000
b101010011 %
1"
#8500000
b101010100 %
0"
#8525000
b101010101 %
1"
#8550000
b101010110 %
0"
#8575000
b101010111 %
1"
#8600000
b101011000 %
0"
#8625000
b101011001 %
1"
#8650000
b101011010 %
0"
#8675000
b101011011 %
1"
#8700000
b101011100 %
0"
#8725000
b101011101 %
1"
#8750000
b101011110 %
0"
#8775000
b101011111 %
1"
#8800000
b101100000 %
0"
#8825000
b101100001 %
1"
#8850000
b101100010 %
0"
#8875000
b101100011 %
1"
#8900000
b101100100 %
0"
#8925000
b101100101 %
1"
#8950000
b101100110 %
0"
#8975000
b101100111 %
1"
#9000000
b101101000 %
0"
#9025000
b101101001 %
1"
#9050000
b101101010 %
0"
#9075000
b101101011 %
1"
#9100000
b101101100 %
0"
#9125000
b101101101 %
1"
#9150000
b101101110 %
0"
#9175000
b101101111 %
1"
#9200000
b101110000 %
0"
#9225000
b101110001 %
1"
#9250000
b101110010 %
0"
#9275000
b101110011 %
1"
#9300000
b101110100 %
0"
#9325000
b101110101 %
1"
#9350000
b101110110 %
0"
#9375000
b101110111 %
1"
#9400000
b101111000 %
0"
#9425000
b101111001 %
1"
#9450000
b101111010 %
0"
#9475000
b101111011 %
1"
#9500000
b101111100 %
0"
#9525000
b101111101 %
1"
#9550000
b101111110 %
0"
#9575000
b101111111 %
1"
#9600000
b110000000 %
0"
#9625000
b110000001 %
1"
#9650000
b110000010 %
0"
#9675000
b110000011 %
1"
#9700000
b110000100 %
0"
#9725000
b110000101 %
1"
#9750000
b110000110 %
0"
#9775000
b110000111 %
1"
#9800000
b110001000 %
0"
#9825000
b110001001 %
1"
#9850000
b110001010 %
0"
#9875000
b110001011 %
1"
#9900000
b110001100 %
0"
#9925000
b110001101 %
1"
#9950000
b110001110 %
0"
#9975000
b110001111 %
1"
#10000000
b110010000 %
0"
#10025000
b110010001 %
1"
#10050000
b110010010 %
0"
#10075000
b110010011 %
1"
#10100000
b110010100 %
0"
#10125000
b110010101 %
1"
#10150000
b110010110 %
0"
#10175000
b110010111 %
1"
#10200000
b110011000 %
0"
#10225000
b110011001 %
1"
#10250000
b110011010 %
0"
#10275000
b110011011 %
1"
#10300000
b110011100 %
0"
#10325000
b110011101 %
1"
#10350000
b110011110 %
0"
#10375000
b110011111 %
1"
#10400000
b110100000 %
0"
#10425000
b110100001 %
1"
#10450000
b110100010 %
0"
#10475000
b110100011 %
1"
#10500000
b110100100 %
0"
#10525000
b110100101 %
1"
#10550000
b110100110 %
0"
#10575000
b110100111 %
1"
#10600000
b110101000 %
0"
#10625000
b110101001 %
1"
#10650000
b110101010 %
0"
#10675000
b110101011 %
1"
#10700000
b110101100 %
0"
#10725000
b110101101 %
1"
#10750000
b110101110 %
0"
#10775000
b110101111 %
1"
#10800000
b110110000 %
0"
#10825000
b110110001 %
1"
#10850000
b110110010 %
0"
#10875000
b110110011 %
1"
#10900000
b110110100 %
0"
#10925000
b110110101 %
1"
#10950000
b110110110 %
0"
#10975000
b110110111 %
1"
#11000000
b110111000 %
0"
#11025000
b110111001 %
1"
#11050000
b110111010 %
0"
#11075000
b110111011 %
1"
#11100000
b110111100 %
0"
#11125000
b110111101 %
1"
#11150000
b110111110 %
0"
#11175000
b110111111 %
1"
#11200000
b111000000 %
0"
#11225000
b111000001 %
1"
#11250000
b111000010 %
0"
#11275000
b111000011 %
1"
#11300000
b111000100 %
0"
#11325000
b111000101 %
1"
#11350000
b111000110 %
0"
#11375000
b111000111 %
1"
#11400000
b111001000 %
0"
#11425000
b111001001 %
1"
#11450000
b111001010 %
0"
#11475000
b111001011 %
1"
#11500000
b111001100 %
0"
#11525000
b111001101 %
1"
#11550000
b111001110 %
0"
#11575000
b111001111 %
1"
#11600000
b111010000 %
0"
#11625000
b111010001 %
1"
#11650000
b111010010 %
0"
#11675000
b111010011 %
1"
#11700000
b111010100 %
0"
#11725000
b111010101 %
1"
#11750000
b111010110 %
0"
#11775000
b111010111 %
1"
#11800000
b111011000 %
0"
#11825000
b111011001 %
1"
#11850000
b111011010 %
0"
#11875000
b111011011 %
1"
#11900000
b111011100 %
0"
#11925000
b111011101 %
1"
#11950000
b111011110 %
0"
#11975000
b111011111 %
1"
#12000000
b111100000 %
0"
#12025000
b111100001 %
1"
#12050000
b111100010 %
0"
#12075000
b111100011 %
1"
#12100000
b111100100 %
0"
#12125000
b111100101 %
1"
#12150000
b111100110 %
0"
#12175000
b111100111 %
1"
#12200000
b111101000 %
0"
#12225000
b111101001 %
1"
#12250000
b111101010 %
0"
#12275000
b111101011 %
1"
#12300000
b111101100 %
0"
#12325000
b111101101 %
1"
#12350000
b111101110 %
0"
#12375000
b111101111 %
1"
#12400000
b111110000 %
0"
#12425000
b111110001 %
1"
#12450000
b111110010 %
0"
#12475000
b111110011 %
1"
#12500000
b111110100 %
0"
#12525000
b111110101 %
1"
#12550000
b111110110 %
0"
#12575000
b111110111 %
1"
#12600000
b111111000 %
0"
#12625000
b111111001 %
1"
#12650000
b111111010 %
0"
#12675000
b111111011 %
1"
#12700000
b111111100 %
0"
#12725000
b111111101 %
1"
#12750000
b111111110 %
0"
#12775000
b111111111 %
1"
#12800000
b1000000000 %
0"
#12825000
b1000000001 %
1"
#12850000
b1000000010 %
0"
#12875000
b1000000011 %
1"
#12900000
b1000000100 %
0"
#12925000
b1000000101 %
1"
#12950000
b1000000110 %
0"
#12975000
b1000000111 %
1"
#13000000
b1000001000 %
0"
#13025000
b1000001001 %
1"
#13050000
b1000001010 %
0"
#13075000
b1000001011 %
1"
#13100000
b1000001100 %
0"
#13125000
b1000001101 %
1"
#13150000
b1000001110 %
0"
#13175000
b1000001111 %
1"
#13200000
b1000010000 %
0"
#13225000
b1000010001 %
1"
#13250000
b1000010010 %
0"
#13275000
b1000010011 %
1"
#13300000
b1000010100 %
0"
#13325000
b1000010101 %
1"
#13350000
b1000010110 %
0"
#13375000
b1000010111 %
1"
#13400000
b1000011000 %
0"
#13425000
b1000011001 %
1"
#13450000
b1000011010 %
0"
#13475000
b1000011011 %
1"
#13500000
b1000011100 %
0"
#13525000
b1000011101 %
1"
#13550000
b1000011110 %
0"
#13575000
b1000011111 %
1"
#13600000
b1000100000 %
0"
#13625000
b1000100001 %
1"
#13650000
b1000100010 %
0"
#13675000
b1000100011 %
1"
#13700000
b1000100100 %
0"
#13725000
b1000100101 %
1"
#13750000
b1000100110 %
0"
#13775000
b1000100111 %
1"
#13800000
b1000101000 %
0"
#13825000
b1000101001 %
1"
#13850000
b1000101010 %
0"
#13875000
b1000101011 %
1"
#13900000
b1000101100 %
0"
#13925000
b1000101101 %
1"
#13950000
b1000101110 %
0"
#13975000
b1000101111 %
1"
#14000000
b1000110000 %
0"
#14025000
b1000110001 %
1"
#14050000
b1000110010 %
0"
#14075000
b1000110011 %
1"
#14100000
b1000110100 %
0"
#14125000
b1000110101 %
1"
#14150000
b1000110110 %
0"
#14175000
b1000110111 %
1"
#14200000
b1000111000 %
0"
#14225000
b1000111001 %
1"
#14250000
b1000111010 %
0"
#14275000
b1000111011 %
1"
#14300000
b1000111100 %
0"
#14325000
b1000111101 %
1"
#14350000
b1000111110 %
0"
#14375000
b1000111111 %
1"
#14400000
b1001000000 %
0"
#14425000
b1001000001 %
1"
#14450000
b1001000010 %
0"
#14475000
b1001000011 %
1"
#14500000
b1001000100 %
0"
#14525000
b1001000101 %
1"
#14550000
b1001000110 %
0"
#14575000
b1001000111 %
1"
#14600000
b1001001000 %
0"
#14625000
b1001001001 %
1"
#14650000
b1001001010 %
0"
#14675000
b1001001011 %
1"
#14700000
b1001001100 %
0"
#14725000
b1001001101 %
1"
#14750000
b1001001110 %
0"
#14775000
b1001001111 %
1"
#14800000
b1001010000 %
0"
#14825000
b1001010001 %
1"
#14850000
b1001010010 %
0"
#14875000
b1001010011 %
1"
#14900000
b1001010100 %
0"
#14925000
b1001010101 %
1"
#14950000
b1001010110 %
0"
#14975000
b1001010111 %
1"
#15000000
b1001011000 %
0"
#15025000
b1001011001 %
1"
#15050000
b1001011010 %
0"
#15075000
b1001011011 %
1"
#15100000
b1001011100 %
0"
#15125000
b1001011101 %
1"
#15150000
b1001011110 %
0"
#15175000
b1001011111 %
1"
#15200000
b1001100000 %
0"
#15225000
b1001100001 %
1"
#15250000
b1001100010 %
0"
#15275000
b1001100011 %
1"
#15300000
b1001100100 %
0"
#15325000
b1001100101 %
1"
#15350000
b1001100110 %
0"
#15375000
b1001100111 %
1"
#15400000
b1001101000 %
0"
#15425000
b1001101001 %
1"
#15450000
b1001101010 %
0"
#15475000
b1001101011 %
1"
#15500000
b1001101100 %
0"
#15525000
b1001101101 %
1"
#15550000
b1001101110 %
0"
#15575000
b1001101111 %
1"
#15600000
b1001110000 %
0"
#15625000
b1001110001 %
1"
#15650000
b1001110010 %
0"
#15675000
b1001110011 %
1"
#15700000
b1001110100 %
0"
#15725000
b1001110101 %
1"
#15750000
b1001110110 %
0"
#15775000
b1001110111 %
1"
#15800000
b1001111000 %
0"
#15825000
b1001111001 %
1"
#15850000
b1001111010 %
0"
#15875000
b1001111011 %
1"
#15900000
b1001111100 %
0"
#15925000
b1001111101 %
1"
#15950000
b1001111110 %
0"
#15975000
b1001111111 %
1"
#16000000
b1010000000 %
0"
#16025000
b1010000001 %
1"
#16050000
b1010000010 %
0"
#16075000
b1010000011 %
1"
#16100000
b1010000100 %
0"
#16125000
b1010000101 %
1"
#16150000
b1010000110 %
0"
#16175000
b1010000111 %
1"
#16200000
b1010001000 %
0"
#16225000
b1010001001 %
1"
#16250000
b1010001010 %
0"
#16275000
b1010001011 %
1"
#16300000
b1010001100 %
0"
#16325000
b1010001101 %
1"
#16350000
b1010001110 %
0"
#16375000
b1010001111 %
1"
#16400000
b1010010000 %
0"
#16425000
b1010010001 %
1"
#16450000
b1010010010 %
0"
#16475000
b1010010011 %
1"
#16500000
b1010010100 %
0"
#16525000
b1010010101 %
1"
#16550000
b1010010110 %
0"
#16575000
b1010010111 %
1"
#16600000
b1010011000 %
0"
#16625000
b1010011001 %
1"
#16650000
b1010011010 %
0"
#16675000
b1010011011 %
1"
#16700000
b1010011100 %
0"
#16725000
b1010011101 %
1"
#16750000
b1010011110 %
0"
#16775000
b1010011111 %
1"
#16800000
b1010100000 %
0"
#16825000
b1010100001 %
1"
#16850000
b1010100010 %
0"
#16875000
b1010100011 %
1"
#16900000
b1010100100 %
0"
#16925000
b1010100101 %
1"
#16950000
b1010100110 %
0"
#16975000
b1010100111 %
1"
#17000000
b1010101000 %
0"
#17025000
b1010101001 %
1"
#17050000
b1010101010 %
0"
#17075000
b1010101011 %
1"
#17100000
b1010101100 %
0"
#17125000
b1010101101 %
1"
#17150000
b1010101110 %
0"
#17175000
b1010101111 %
1"
#17200000
b1010110000 %
0"
#17225000
b1010110001 %
1"
#17250000
b1010110010 %
0"
#17275000
b1010110011 %
1"
#17300000
b1010110100 %
0"
#17325000
b1010110101 %
1"
#17350000
b1010110110 %
0"
#17375000
b1010110111 %
1"
#17400000
b1010111000 %
0"
#17425000
b1010111001 %
1"
#17450000
b1010111010 %
0"
#17475000
b1010111011 %
1"
#17500000
b1010111100 %
0"
#17525000
b1010111101 %
1"
#17550000
b1010111110 %
0"
#17575000
b1010111111 %
1"
#17600000
b1011000000 %
0"
#17625000
b1011000001 %
1"
#17650000
b1011000010 %
0"
#17675000
b1011000011 %
1"
#17700000
b1011000100 %
0"
#17725000
b1011000101 %
1"
#17750000
b1011000110 %
0"
#17775000
b1011000111 %
1"
#17800000
b1011001000 %
0"
#17825000
b1011001001 %
1"
#17850000
b1011001010 %
0"
#17875000
b1011001011 %
1"
#17900000
b1011001100 %
0"
#17925000
b1011001101 %
1"
#17950000
b1011001110 %
0"
#17975000
b1011001111 %
1"
#18000000
b1011010000 %
0"
#18025000
b1011010001 %
1"
#18050000
b1011010010 %
0"
#18075000
b1011010011 %
1"
#18100000
b1011010100 %
0"
#18125000
b1011010101 %
1"
#18150000
b1011010110 %
0"
#18175000
b1011010111 %
1"
#18200000
b1011011000 %
0"
#18225000
b1011011001 %
1"
#18250000
b1011011010 %
0"
#18275000
b1011011011 %
1"
#18300000
b1011011100 %
0"
#18325000
b1011011101 %
1"
#18350000
b1011011110 %
0"
#18375000
b1011011111 %
1"
#18400000
b1011100000 %
0"
#18425000
b1011100001 %
1"
#18450000
b1011100010 %
0"
#18475000
b1011100011 %
1"
#18500000
b1011100100 %
0"
#18525000
b1011100101 %
1"
#18550000
b1011100110 %
0"
#18575000
b1011100111 %
1"
#18600000
b1011101000 %
0"
#18625000
b1011101001 %
1"
#18650000
b1011101010 %
0"
#18675000
b1011101011 %
1"
#18700000
b1011101100 %
0"
#18725000
b1011101101 %
1"
#18750000
b1011101110 %
0"
#18775000
b1011101111 %
1"
#18800000
b1011110000 %
0"
#18825000
b1011110001 %
1"
#18850000
b1011110010 %
0"
#18875000
b1011110011 %
1"
#18900000
b1011110100 %
0"
#18925000
b1011110101 %
1"
#18950000
b1011110110 %
0"
#18975000
b1011110111 %
1"
#19000000
b1011111000 %
0"
#19025000
b1011111001 %
1"
#19050000
b1011111010 %
0"
#19075000
b1011111011 %
1"
#19100000
b1011111100 %
0"
#19125000
b1011111101 %
1"
#19150000
b1011111110 %
0"
#19175000
b1011111111 %
1"
#19200000
b1100000000 %
0"
#19225000
b1100000001 %
1"
#19250000
b1100000010 %
0"
#19275000
b1100000011 %
1"
#19300000
b1100000100 %
0"
#19325000
b1100000101 %
1"
#19350000
b1100000110 %
0"
#19375000
b1100000111 %
1"
#19400000
b1100001000 %
0"
#19425000
b1100001001 %
1"
#19450000
b1100001010 %
0"
#19475000
b1100001011 %
1"
#19500000
b1100001100 %
0"
#19525000
b1100001101 %
1"
#19550000
b1100001110 %
0"
#19575000
b1100001111 %
1"
#19600000
b1100010000 %
0"
#19625000
b1100010001 %
1"
#19650000
b1100010010 %
0"
#19675000
b1100010011 %
1"
#19700000
b1100010100 %
0"
#19725000
b1100010101 %
1"
#19750000
b1100010110 %
0"
#19775000
b1100010111 %
1"
#19800000
b1100011000 %
0"
#19825000
b1100011001 %
1"
#19850000
b1100011010 %
0"
#19875000
b1100011011 %
1"
#19900000
b1100011100 %
0"
#19925000
b1100011101 %
1"
#19950000
b1100011110 %
0"
#19975000
b1100011111 %
1"
#20000000
b1100100000 %
0"
#20025000
b1100100001 %
1"
#20050000
b1100100010 %
0"
#20075000
b1100100011 %
1"
#20100000
b1100100100 %
0"
#20125000
b1100100101 %
1"
#20150000
b1100100110 %
0"
#20175000
b1100100111 %
1"
#20200000
b1100101000 %
0"
#20225000
b1100101001 %
1"
#20250000
b1100101010 %
0"
#20275000
b1100101011 %
1"
#20300000
b1100101100 %
0"
#20325000
b1100101101 %
1"
#20350000
b1100101110 %
0"
#20375000
b1100101111 %
1"
#20400000
b1100110000 %
0"
#20425000
b1100110001 %
1"
#20450000
b1100110010 %
0"
#20475000
b1100110011 %
1"
#20500000
b1100110100 %
0"
#20525000
b1100110101 %
1"
#20550000
b1100110110 %
0"
#20575000
b1100110111 %
1"
#20600000
b1100111000 %
0"
#20625000
b1100111001 %
1"
#20650000
b1100111010 %
0"
#20675000
b1100111011 %
1"
#20700000
b1100111100 %
0"
#20725000
b1100111101 %
1"
#20750000
b1100111110 %
0"
#20775000
b1100111111 %
1"
#20800000
b1101000000 %
0"
#20825000
b1101000001 %
1"
#20850000
b1101000010 %
0"
#20875000
b1101000011 %
1"
#20900000
b1101000100 %
0"
#20925000
b1101000101 %
1"
#20950000
b1101000110 %
0"
#20975000
b1101000111 %
1"
#21000000
b1101001000 %
0"
#21025000
b1101001001 %
1"
#21050000
b1101001010 %
0"
#21075000
b1101001011 %
1"
#21100000
b1101001100 %
0"
#21125000
b1101001101 %
1"
#21150000
b1101001110 %
0"
#21175000
b1101001111 %
1"
#21200000
b1101010000 %
0"
#21225000
b1101010001 %
1"
#21250000
b1101010010 %
0"
#21275000
b1101010011 %
1"
#21300000
b1101010100 %
0"
#21325000
b1101010101 %
1"
#21350000
b1101010110 %
0"
#21375000
b1101010111 %
1"
#21400000
b1101011000 %
0"
#21425000
b1101011001 %
1"
#21450000
b1101011010 %
0"
#21475000
b1101011011 %
1"
#21500000
b1101011100 %
0"
#21525000
b1101011101 %
1"
#21550000
b1101011110 %
0"
#21575000
b1101011111 %
1"
#21600000
b1101100000 %
0"
#21625000
b1101100001 %
1"
#21650000
b1101100010 %
0"
#21675000
b1101100011 %
1"
#21700000
b1101100100 %
0"
#21725000
b1101100101 %
1"
#21750000
b1101100110 %
0"
#21775000
b1101100111 %
1"
#21800000
b1101101000 %
0"
#21825000
b1101101001 %
1"
#21850000
b1101101010 %
0"
#21875000
b1101101011 %
1"
#21900000
b1101101100 %
0"
#21925000
b1101101101 %
1"
#21950000
b1101101110 %
0"
#21975000
b1101101111 %
1"
#22000000
b1101110000 %
0"
#22025000
b1101110001 %
1"
#22050000
b1101110010 %
0"
#22075000
b1101110011 %
1"
#22100000
b1101110100 %
0"
#22125000
b1101110101 %
1"
#22150000
b1101110110 %
0"
#22175000
b1101110111 %
1"
#22200000
b1101111000 %
0"
#22225000
b1101111001 %
1"
#22250000
b1101111010 %
0"
#22275000
b1101111011 %
1"
#22300000
b1101111100 %
0"
#22325000
b1101111101 %
1"
#22350000
b1101111110 %
0"
#22375000
b1101111111 %
1"
#22400000
b1110000000 %
0"
#22425000
b1110000001 %
1"
#22450000
b1110000010 %
0"
#22475000
b1110000011 %
1"
#22500000
b1110000100 %
0"
#22525000
b1110000101 %
1"
#22550000
b1110000110 %
0"
#22575000
b1110000111 %
1"
#22600000
b1110001000 %
0"
#22625000
b1110001001 %
1"
#22650000
b1110001010 %
0"
#22675000
b1110001011 %
1"
#22700000
b1110001100 %
0"
#22725000
b1110001101 %
1"
#22750000
b1110001110 %
0"
#22775000
b1110001111 %
1"
#22800000
b1110010000 %
0"
#22825000
b1110010001 %
1"
#22850000
b1110010010 %
0"
#22875000
b1110010011 %
1"
#22900000
b1110010100 %
0"
#22925000
b1110010101 %
1"
#22950000
b1110010110 %
0"
#22975000
b1110010111 %
1"
#23000000
b1110011000 %
0"
#23025000
b1110011001 %
1"
#23050000
b1110011010 %
0"
