InstructionFetch/insCache/insCache.v
`timescale 1ns / 1ps

module insCache(clk,
		rstn,
		iaddr,
		imem_in,
		ohit,
		oins);
   input clk, rstn;
   input [31:0] iaddr;
   input [127:0] imem_in;
   output reg [31:0] oins;
   output reg	     ohit;

   reg [154:0] content[3:0];

   // wire [3:0] tag[25:0];
   // wire [3:0] valid;
   // wire [3:0] set[127:0];

   reg [1:0] counter;

   integer    i;

   always @(negedge rstn)
     begin
	counter = 0;
	ohit = 0;
	oins = 0;
	for (i = 0; i < 4; i = i + 1)
	  begin
	     content[i] = 0;
	  end
     end

   always @(posedge clk)
     begin
	if (content[iaddr[5:4]][0] == 1'b1 &&
	    iaddr[31:6] == content[iaddr[5:4]][154:129])
	  begin // hit?
	     case (iaddr[3:2])
	       2'b00 : oins = content[iaddr[5:4]][32:1];
	       2'b01 : oins = content[iaddr[5:4]][64:33];
	       2'b10 : oins = content[iaddr[5:4]][96:65];
	       2'b11 : oins = content[iaddr[5:4]][128:97];
	     endcase
	     ohit = 1;
	  end
	else
	  begin // miss
	     ohit = 0;
	     if (counter == 3)
	       begin
		  content[iaddr[5:4]] = {imem_in[31:6],
					 imem_in[127:96],
					 imem_in[95:64],
					 imem_in[63:32],
					 imem_in[31:0],
					 1'b1};
		  counter = 0;
		  case (iaddr[3:2])
		    2'b00 : oins = content[iaddr[5:4]][32:1];
		    2'b01 : oins = content[iaddr[5:4]][64:33];
		    2'b10 : oins = content[iaddr[5:4]][96:65];
		    2'b11 : oins = content[iaddr[5:4]][128:97];
		  endcase
		  ohit = 1;
	       end
	     else
	       begin
		  counter = counter + 1;
	       end			// if counter
	  end			// if miss
     end				// always


endmodule // main

InstructionFetch/insCache/insCache_test.v
`timescale 1ns / 1ps

module main_test;

   // Inputs
   reg clk, resetn=1;
   reg [31:0] iaddr;
   reg [127:0] imem_in;
   
   // Outputs
   wire [31:0] oins;
   wire        ohit;
   
   integer     i;
   
   // Instantiate the Unit Under Test (UUT)
   insCache uut(clk,
		resetn,
		iaddr,
		imem_in,
		ohit,
		oins
		);

   initial begin
      /// Initialize Inputs
      #10;
      resetn = 0;
      #10;
      iaddr = 7;
      #90;
      imem_in = {32'hDEADBEEF ,32'hABABABAB 
		 ,32'hCDCDCDCD, 32'hEFEFEFEF};
      #190;
      iaddr = 0;
      
      
   end

   initial begin
      clk = 0;
      for (i = 0; i < 20; i = i + 1)
	#25 clk = ~clk;
   end


   initial begin
      $dumpfile("./insCache.vcd");
      $dumpvars;
   end

endmodule

InstructionFetch/insCache/insCache.vcd
$date
	Tue Oct 23 20:27:50 2018
$end
$version
	Icarus Verilog
$end
$timescale
	1ps
$end
$scope module main_test $end
$var wire 32 ! oins [31:0] $end
$var wire 1 " ohit $end
$var reg 1 # clk $end
$var reg 32 $ iaddr [31:0] $end
$var reg 128 % imem_in [127:0] $end
$var reg 1 & resetn $end
$var integer 32 ' i [31:0] $end
$scope module uut $end
$var wire 1 # clk $end
$var wire 32 ( iaddr [31:0] $end
$var wire 128 ) imem_in [127:0] $end
$var wire 1 & rstn $end
$var reg 2 * counter [1:0] $end
$var reg 1 " ohit $end
$var reg 32 + oins [31:0] $end
$var integer 32 , i [31:0] $end
$upscope $end
$upscope $end
$enddefinitions $end
#0
$dumpvars
bx ,
bx +
bx *
bx )
bx (
b0 '
1&
bx %
bx $
0#
x"
bx !
$end
#10000
b100 ,
b0 !
b0 +
0"
b0 *
0&
#20000
b111 $
b111 (
#25000
b1 *
b1 '
1#
#50000
b10 '
0#
#75000
b10 *
b11 '
1#
#100000
b100 '
0#
#110000
b11011110101011011011111011101111101010111010101110101011101010111100110111001101110011011100110111101111111011111110111111101111 %
b11011110101011011011111011101111101010111010101110101011101010111100110111001101110011011100110111101111111011111110111111101111 )
#125000
b11 *
b101 '
1#
#150000
b110 '
0#
#175000
1"
b11001101110011011100110111001101 !
b11001101110011011100110111001101 +
b0 *
b111 '
1#
#200000
b1000 '
0#
#225000
b1 *
0"
b1001 '
1#
#250000
b1010 '
0#
#275000
b10 *
b1011 '
1#
#300000
b1100 '
0#
b0 $
b0 (
#325000
b11 *
b1101 '
1#
#350000
b1110 '
0#
#375000
1"
b11101111111011111110111111101111 !
b11101111111011111110111111101111 +
b0 *
b1111 '
1#
#400000
b10000 '
0#
#425000
b1 *
0"
b10001 '
1#
#450000
b10010 '
0#
#475000
b10 *
b10011 '
1#
#500000
b10100 '
0#
